Workbook

Sheet Dashboard
H2: Britannia Industries – FY26 Financial Outlook
H6: Scenario: | I6: ='Forecast Model'!G2 -> Base
F10: Revenue (FY26) | I10: EBITDA (FY26) | L10: EBITDA Margin
F12: ='Forecast Model'!C4 -> 19198.657 | I12: ='Forecast Model'!C14 -> 3314.6201 | L12: ='Forecast Model'!C16 -> 0.17264854
AA14: Year | AB14: EBITDA Margin
AA15: FY23 | AB15: ='Historical Data Calculations'!B20 -> 0.1736696
AA17: FY24 | AB17: =Table6[[#This Row],[FY24]] -> 0.2026743
AA19: FY25 | AB19: ='Historical Data Calculations'!D20 -> 0.17762964
AA21: FY26 | AB21: ='Forecast Model'!C16 -> 0.17264854
F36: Base Case | I36: Upside Case | L36: Downside Case
F38: Revenue | G38: 19198.7 | I38: Revenue | J38: 19557.5 | L38: Revenue | M38: 18750.1
F39: EBITDA | G39: 3314.6 | I39: EBITDA | J39: 3804.6 | L39: EBITDA | M39: 2725.4
F40: Margin | G40: 0.173 | I40: Margin | J40: 0.195 | L40: Margin | M40: 0.145

Sheet Historical Data
A1: Line Item | B1: FY23 | C1: FY24 | D1: FY25
A2: Revenue from Operations | B2: 16300.55 | C2: 16769.27 | D2: 17942.67
A3: Cost of Materials Consumed | B3: 8326.7 | C3: 8546.89 | D3: 9859.45
A4: Purchase of Stock-in-Trade | B4: 1337.13 | C4: 941.48 | D4: 809.35
A5: Change in Inventory | B5: -72.53 | C5: 3.66 | D5: -64.75
A6: Employee Benefits Expense | B6: 658.38 | C6: 708.7 | D6: 704.59
A7: Advertising & Sales Promotion | B7: 675.05 | C7: 694.5 | D7: 560.1
A8: Other Expenses | B8: 3219.96 | C8: 3398.7 | D8: 3446.88
A9: Adjusted Other Expenses | B9: =B8-B7 -> 2544.91 | C9: =C8-C7 -> 2704.2 | D9: =D8-D7 -> 2886.78
A10: Depreciation & Amortisation | B10: 225.91 | C10: 300.46 | D10: 313.34
A11: Finance Cost | B11: 169.1 | C11: 164 | D11: 138.8
A12: Exceptional Items | B12: -375.6 | C12: 2.9 | D12: 24.79
A13: Profit Before Tax | B13: 3032.77 | C13: 2913.47 | D13: 2926.57
A14: Profit After Tax | B14: 2316.32 | C14: 2134.22 | D14: 2177.86

Sheet Historical Data Calculations
A1: Line Item | B1: FY23 | C1: FY24 | D1: FY25
A2: Revenue from Operations | B2: ='Historical Data'!B2 -> 16300.55 | C2: ='Historical Data'!C2 -> 16769.27 | D2: ='Historical Data'!D2 -> 17942.67
A4: Cost of Materials Consumed | B4: ='Historical Data'!B3 -> 8326.7 | C4: ='Historical Data'!C3 -> 8546.89 | D4: ='Historical Data'!D3 -> 9859.45
A5: Purchase of Stock-in-Trade | B5: ='Historical Data'!B4 -> 1337.13 | C5: ='Historical Data'!C4 -> 941.48 | D5: ='Historical Data'!D4 -> 809.35
A6: Change in Inventory | B6: ='Historical Data'!B5 -> -72.53 | C6: ='Historical Data'!C5 -> 3.66 | D6: ='Historical Data'!D5 -> -64.75
A7: Total Raw Material Cost | B7: =B4+B5+B6 -> 9591.3 | C7: =C4+C5+C6 -> 9492.03 | D7: =D4+D5+D6 -> 10604.05
A8: Raw Material % | B8: =B7/B2 -> 0.58840346 | C8: =C7/C2 -> 0.56603716 | D8: =D7/D2 -> 0.59099621
A10: Employee Benefits Expense | B10: ='Historical Data'!B6 -> 658.38 | C10: ='Historical Data'!C6 -> 708.7 | D10: ='Historical Data'!D6 -> 704.59
A11: Employee % | B11: =B10/B2 -> 0.040390048 | C11: =C10/C2 -> 0.042261828 | D11: =D10/D2 -> 0.039268961
A13: Advertising & Sales Promotion | B13: ='Historical Data'!B7 -> 675.05 | C13: ='Historical Data'!C7 -> 694.5 | D13: ='Historical Data'!D7 -> 560.1
A14: Advertising % | B14: =B13/B2 -> 0.041412713 | C14: =C13/C2 -> 0.041415041 | D14: =D13/D2 -> 0.03121609
A16: Other Expenses | B16: ='Historical Data'!B8 -> 3219.96 | C16: ='Historical Data'!C8 -> 3398.7 | D16: ='Historical Data'!D8 -> 3446.88
A17: Other Expense % | B17: =B16/B2 -> 0.19753689 | C17: =C16/C2 -> 0.2026743 | D17: =D16/D2 -> 0.19210519
A19: EBITDA | B19: =B2-B7-B10-B16 -> 2830.91 | C19: =C2-C7-C10-C16 -> 3169.84 | D19: =D2-D7-D10-D16 -> 3187.15
A20: EBITDA Margin % | B20: =B19/B2 -> 0.1736696 | C20: =C19/C2 -> 0.18902671 | D20: =D19/D2 -> 0.17762964
A22: Depreciation & Amortisation | B22: ='Historical Data'!B10 -> 225.91 | C22: ='Historical Data'!C10 -> 300.46 | D22: ='Historical Data'!D10 -> 313.34
A23: Finance Cost | B23: ='Historical Data'!B11 -> 169.1 | C23: ='Historical Data'!C11 -> 164 | D23: ='Historical Data'!D11 -> 138.8
A24: Exceptional Items | B24: ='Historical Data'!B12 -> -375.6 | C24: ='Historical Data'!C12 -> 2.9 | D24: ='Historical Data'!D12 -> 24.79
A25: Profit Before Tax | B25: ='Historical Data'!B13 -> 3032.77 | C25: ='Historical Data'!C13 -> 2913.47 | D25: ='Historical Data'!D13 -> 2926.57
A26: Adjusted Profit Before Tax | B26: =B25+B24 -> 2657.17 | C26: =C25+C24 -> 2916.37 | D26: =D25+D24 -> 2951.36
A27: Profit After Tax | B27: ='Historical Data'!B14 -> 2316.32 | C27: ='Historical Data'!C14 -> 2134.22 | D27: ='Historical Data'!D14 -> 2177.86
A28: Net Margin % | B28: =B27/B2 -> 0.14210073 | C28: =C27/C2 -> 0.1272697 | D28: =D27/D2 -> 0.12137881

Sheet Trend Analysis
A1: Britannia Industries – 3-Year Trend Analysis
A3: Metric | B3: FY23 | C3: FY24 | D3: FY25
A4: Revenue (₹ Cr) | B4: ='Historical Data'!B2 -> 16300.55 | C4: ='Historical Data'!C2 -> 16769.27 | D4: ='Historical Data'!D2 -> 17942.67
A6: Revenue Growth % | C6: =(C4-B4)/B4 -> 0.028754858 | D6: =(D4-C4)/C4 -> 0.069973231
A9: Metric | B9: FY23 | C9: FY24 | D9: FY25
A10: EBITDA (₹ Cr) | B10: ='Historical Data Calculations'!B19 -> 2830.91 | C10: ='Historical Data Calculations'!C19 -> 3169.84 | D10: ='Historical Data Calculations'!D19 -> 3187.15
A12: EBITDA Growth % | C12: =(C10-B10)/B10 -> 0.11972475 | D12: =(D10-C10)/C10 -> 0.0054608434
A14: EBITDA Margin % | B14: ='Historical Data Calculations'!B20 -> 0.1736696 | C14: ='Historical Data Calculations'!C20 -> 0.18902671 | D14: ='Historical Data Calculations'!D20 -> 0.17762964
A18: Metric | B18: FY23 | C18: FY24 | D18: FY25
A19: Profit After Tax (₹ Cr) | B19: ='Historical Data'!B14 -> 2316.32 | C19: ='Historical Data'!C14 -> 2134.22 | D19: ='Historical Data'!D14 -> 2177.86
A21: PAT Growth % | C21: =(C19-B19)/B19 -> -0.078616081 | D21: =(D19-C19)/C19 -> 0.020447751
A23: Net Margin % | B23: ='Historical Data Calculations'!B28 -> 0.14210073 | C23: ='Historical Data Calculations'!C28 -> 0.1272697 | D23: ='Historical Data Calculations'!D28 -> 0.12137881

Sheet Driver Thinking
A1: Britannia Industries – Key Business Drivers
A4: Financial Line | B4: Key Driver | C4: Significance | D4: Historical Observation
A6: Revenue | B6: Volume Growth | C6: Drives top-line expansion | D6: Growth accelerated in FY25
A8: Revenue | B8: Price Increase | C8: Protects margins during inflation | D8: FY25 likely price-led growth
A10: Raw Material Cost | B10: Commodity Prices | C10: 60% of revenue, biggest cost | D10: % increased in FY25
A12: Raw Material Cost | B12: Inventory Movement | C12: Short-term cost impact | D12: Volatile across years
A14: Employee Cost | B14: Salary Inflation | C14: Semi-fixed cost | D14: Stable % of revenue
A16: Advertising | B16: Brand Investment | C16: Drives demand | D16: ~3% stable trend
A18: EBITDA Margin | B18: Operating Leverage | C18: Revenue spreads fixed cost | D18: Improved in FY24
A20: Net Profit | B20: Exceptional Items | C20: Distorts comparability | D20: FY23 had large gain

Sheet Assumptions
A1: Britannia Industries – FY26 Planning Assumptions
A3: Assumption | B3: Base Case | C3: Upside | D3: Downside | E3: Rationale
A4: Revenue Growth % | B4: 0.07 | C4: 0.09 | D4: 0.045 | E4: Growth normalization after FY25
A8: Assumption | B8: Base Case | C8: Upside | D8: Downside | E8: Rationale
A9: Raw Material % of Revenue | B9: 0.591 | C9: 0.578 | D9: 0.608 | E9: Commodity volatility
A10: Advertising % of Revenue | B10: 0.038 | C10: 0.035 | D10: 0.042 | E10: Margin vs growth trade-off
A11: Employee Growth % | B11: 0.045 | C11: 0.04 | D11: 0.055 | E11: Salary inflation
A14: Assumption | B14: Base Case | C14: Upside | D14: Downside | E14: Rationale
A15: Other Expense % of Revenue | B15: 0.195 | C15: 0.19 | D15: 0.2 | E15: Efficiency vs cost pressure
A16: Depreciation Growth % | B16: 0.05 | C16: 0.04 | D16: 0.06 | E16: Capex impact
A17: Finance Cost Growth % | B17: 0.03 | C17: 0.02 | D17: 0.05 | E17: Interest environment
A18: Other Expense % of Revenue(exclude advertising) | B18: 0.16 | C18: 0.155 | D18: 0.165
A22: Assumption | B22: Base | C22: Upside | D22: Downside
A24: Revenue Growth | B24: 0.07 | C24: 0.09 | D24: 0.045
A25: Raw Material % | B25: 0.591 | C25: 0.578 | D25: 0.608
A26: Employee Growth | B26: 0.045 | C26: 0.04 | D26: 0.055
A27: Advertising % | B27: 0.038 | C27: 0.035 | D27: 0.042
A28: Other Expense % | B28: 0.16 | C28: 0.155 | D28: 0.165

Sheet Forecast Model
A1: Britannia Industries – FY26 Forecast
F2: Select Scenario: | G2: Base
B3: Metric | C3: FY26
B4: Revenue | C4: ='Historical Data Calculations'!D2 * (1 + CHOOSE( MATCH(G2,{"Base","Upside","Downside"},0),Assumptions!B24,Assumptions!C24,Assumptions!D24 )) -> 19198.657
B6: Raw Material | C6: =C4 * CHOOSE( MATCH(G2,{"Base","Upside","Downside"},0),Assumptions!B25,Assumptions!C25,Assumptions!D25) -> 11346.406
B8: Employee | C8: ='Historical Data Calculations'!D10 * (1 + CHOOSE( MATCH(G2,{"Base","Upside","Downside"},0),Assumptions!B26,Assumptions!C26,Assumptions!D26 )) -> 736.29655
B10: Advertising | C10: =C4 * CHOOSE( MATCH(G2,{"Base","Upside","Downside"},0),Assumptions!B27,Assumptions!C27,Assumptions!D27 ) -> 729.54896
B12: Other Expense | C12: =C4 * CHOOSE( MATCH(G2,{"Base","Upside","Downside"},0),Assumptions!B28,Assumptions!C28,Assumptions!D28 ) -> 3071.7851
B14: EBITDA | C14: =C4-C6-C8-C10-C12 -> 3314.6201
B16: EBITDA Margin | C16: =C14/C4 -> 0.17264854
